CHANGELOG.txt
COPYRIGHT.txt
README.txt
setup.py
TGCaptcha.egg-info/PKG-INFO
TGCaptcha.egg-info/SOURCES.txt
TGCaptcha.egg-info/dependency_links.txt
TGCaptcha.egg-info/entry_points.txt
TGCaptcha.egg-info/not-zip-safe
TGCaptcha.egg-info/requires.txt
TGCaptcha.egg-info/top_level.txt
tests/__init__.py
tests/test_controller.py
tests/test_mcdermott.py
tests/test_model.py
tests/test_widgets.py
tgcaptcha/__init__.py
tgcaptcha/controller.py
tgcaptcha/model.py
tgcaptcha/release.py
tgcaptcha/validator.py
tgcaptcha/widgets.py
tgcaptcha/plugins/__init__.py
tgcaptcha/plugins/image/__init__.py
tgcaptcha/plugins/image/mcdermott.py
tgcaptcha/plugins/image/vanasco_dowty/__init__.py
tgcaptcha/plugins/image/vanasco_dowty/captcha.py
tgcaptcha/plugins/text/__init__.py
tgcaptcha/plugins/text/random_ascii.py
tgcaptcha/static/fonts/tuffy/LICENSE.txt
tgcaptcha/static/fonts/tuffy/Tuffy.ttf
tgcaptcha/static/fonts/tuffy/Tuffy_Bold.ttf
tgcaptcha/static/fonts/tuffy/Tuffy_Bold_Italic.ttf
tgcaptcha/static/fonts/tuffy/Tuffy_Italic.ttf
tgcaptcha/static/images/favicon.ico
tgcaptcha/static/images/tg_under_the_hood.png
tgcaptcha/static/images/under_the_hood_blue.png
tgcaptcha/template/+package+/config/tgcaptcha.cfg
