Metadata-Version: 1.0
Name: TGCaptcha
Version: 0.11
Summary: A TurboGears CAPTCHA widget for forms.
Home-page: http://code.google.com/p/tgcaptcha/
Author: Patrick Lewis
Author-email: plewis@spamcop.net
License: MIT
Keywords: turbogears.widgets
Platform: UNKNOWN
Classifier: Development Status :: 3 - Alpha
Classifier: Operating System :: OS Independent
Classifier: Programming Language :: Python
Classifier: Topic :: Software Development :: Libraries :: Python Modules
Classifier: Framework :: TurboGears
Classifier: Framework :: TurboGears :: Widgets
